{
  "id": "finance_lease_recognition",
  "title": "Финансовая аренда (лизинг): признание у лизингополучателя",
  "aliases": [
    "учёт лизинга у арендатора",
    "0310 признание"
  ],
  "keywords": [
    "0100",
    "0810",
    "0820",
    "амортизация",
    "НДС",
    "ввод в эксплуатацию,амортизация",
    "ремонт",
    "переоценка",
    "лизинг",
    "оперативная аренда",
    "коммунальные услуги",
    "арендатор",
    "арендодатель",
    "уставный капитал",
    "реализация ОС",
    "безвозмездная передача",
    "выбытие",
    "дивиденды ОС",
    "ликвидация ОС",
    "комиссия ГСБДД",
    "страхование ОСАГО",
    "авто лизинг",
    "0310",
    "0800",
    "7910",
    "6950"
  ],
  "jurisdiction": "UZ",
  "description": "Принятие к учёту объекта по 0310 и признание обязательства по 7910/6950.",
  "conditions": [
    "Принимается объект аренды на 0310.",
    "Обязательства учитываются на 7910 (долгосрочная часть) и 6950 (текущая часть)."
  ],
  "docs_required": [
    "Договор финансовой аренды",
    "График платежей",
    "Акт приёма-передачи"
  ],
  "vat_applicability": "НДС по лизинговым платежам — по условиям договора/ЭСФ.",
  "legal_refs": [
    "Отражайте принятие к учету объекта аренды на счете 0310 «Основные средства, полученные по договору финансовой аренды», а задолженность отражайте как обязательство по счетам 7910 «Финансовая аренда к оплате» и 6950 «Долгосрочные обязательства — текущая часть» (пп. 33–40 НСБУ №21)."
  ],
  "entries": [
    {
      "debit": "0310",
      "credit": "7910",
      "note": "Принят к учету объект лизинга, признано долгосрочное обязательство"
    },
    {
      "debit": "7910",
      "credit": "6950",
      "note": "Перевод части обязательства в текущую задолженность"
    }
  ],
  "examples": [
    {
      "text": "Принят к учету объект лизинга стоимостью 100 000 000 сум, обязательство признано по 7910. Через год часть долга 20 000 000 сум переведена в текущую задолженность (6950).",
      "entries": [
        { "debit": "0310", "credit": "7910", "amount": 100000000 },
        { "debit": "7910", "credit": "6950", "amount": 20000000 }
      ]
    }
  ],
  "version": "1.0",
  "updated_at": "2025-09-21",
  "category_id": "fixed_assets",
  "category_title": "Основные средства",
  "source_category_notes": "Группы ОС: 0110 Земля; 0120 Здания/сооружения; 0130 Машины и оборудование; 0140 Мебель; 0150 Компьютеры; 0160 Транспорт; 0170 Скот; 0180 Насаждения; 0190 Прочие; 0199 Законсервированные.",
  "_text": "Финансовая аренда (лизинг): признание у лизингополучателя · Дт 0310 Кт 7910 — принят к учету объект лизинга | Дт 7910 Кт 6950 — перевод части долга в текущие обязательства"
}
